Metadata-Version: 2.1
Name: failrunner-django
Version: 1.0.4
Summary: A command line tool to run django tests that failed during a travis job
Home-page: https://github.com/harrywhite4/failrunner-django
Author: Harry White
Author-email: harry.white424@gmail.com
License: MIT
Platform: UNKNOWN
Classifier: License :: OSI Approved :: MIT License
Classifier: Topic :: Software Development :: Testing
Classifier: Intended Audience :: Developers
Classifier: Programming Language :: Python
Classifier: Programming Language :: Python :: 3
Classifier: Programming Language :: Python :: 3 :: Only
Classifier: Programming Language :: Python :: 3.5
Classifier: Programming Language :: Python :: 3.6
Classifier: Programming Language :: Python :: 3.7
Requires-Python: >=3.5
